Metadata-Version: 2.1
Name: star-lake-spark
Version: 1.0.0
Summary: Python APIs for using Star Lake with Apache Spark
Home-page: https://github.com/engine-plus/StarLake
Author: EnginePlus Team
Author-email: kehan.cao@mobvista.com
License: Apache-2.0
Keywords: star-lake
Platform: UNKNOWN
Classifier: Development Status :: 5 - Production/Stable
Classifier: Intended Audience :: Developers
Classifier: License :: OSI Approved :: Apache Software License
Classifier: Operating System :: OS Independent
Classifier: Topic :: Software Development :: Libraries :: Python Modules
Classifier: Programming Language :: Python :: 3
Requires-Python: >=3.6
